pyvise/__init__.py
pyvise/account_backend.py
pyvise/base.py
pyvise/configuration.py
pyvise/magic_backend.py
pyvise/models.py
pyvise/session_controller.py
pyvise/settings.py
pyvise/backend/__init__.py
pyvise/backend/account_backend.py
pyvise/backend/magic_backend.py
pyvise/graphy/__init__.py
pyvise/graphy/base.py
pyvise/graphy/client.py
pyvise/routers/__init__.py
pyvise/routers/profile_router.py
pyvise-0.1.0.dist-info/LICENSE
pyvise-0.1.0.dist-info/METADATA
pyvise-0.1.0.dist-info/WHEEL
pyvise-0.1.0.dist-info/top_level.txt
pyvise-0.1.0.dist-info/RECORD
