Metadata-Version: 2.1
Name: pyvise
Version: 0.1.0
Summary: A small authentication package using FastAPI and magic
Home-page: https://github.com/dpayonk/pyvise
Author: Dennis Payonk
Author-email: dennis@payonk.com
License: UNKNOWN
Platform: UNKNOWN
Classifier: Programming Language :: Python :: 3
Classifier: License :: OSI Approved :: MIT License
Classifier: Operating System :: OS Independent
Requires-Python: >=3.7
Requires-Dist: aiofiles (>=0.6.0)
Requires-Dist: dataclasses-json (>=0.5.2)
Requires-Dist: fastapi (>=0.63.0)
Requires-Dist: fastapi-jwt-auth (>=0.5.0)
Requires-Dist: pydantic (>=1.7.3)
Requires-Dist: magic-admin (>=0.0.4)
Requires-Dist: requests (>=2.22.0)
